fin_insight_extract/__init__.py
fin_insight_extract/main.py
fin_insight_extract/prompts.py
fin_insight_extract-2025.12.22075142.dist-info/METADATA
fin_insight_extract-2025.12.22075142.dist-info/WHEEL
fin_insight_extract-2025.12.22075142.dist-info/top_level.txt
fin_insight_extract-2025.12.22075142.dist-info/RECORD
