Metadata-Version: 2.4
Name: fin-insight-extract
Version: 2025.12.22075142
Summary: fin-insight-extract extracts and structures key business and financial insights from unstructured text for analysts and investors.
Author-email: fin-insight-extract <hi@eugene.plus>
License: MIT
Project-URL: Homepage, https://github.com/chigwell/fin-insight-extract
Requires-Python: >=3.9
Requires-Dist: langchain-llm7>=0.0.0
Requires-Dist: llmatch-messages>=0.0.0
Requires-Dist: langchain-core>=0.3.0
